multilabelencoder
